simple_rdp/__init__.py
simple_rdp/_rle.cpython-311-x86_64-linux-gnu.so
simple_rdp/capabilities.py
simple_rdp/client.py
simple_rdp/credssp.py
simple_rdp/display.py
simple_rdp/input.py
simple_rdp/mcs.py
simple_rdp/pdu.py
simple_rdp/rle.py
simple_rdp-0.1.0.dist-info/METADATA
simple_rdp-0.1.0.dist-info/WHEEL
simple_rdp-0.1.0.dist-info/licenses/LICENSE
simple_rdp-0.1.0.dist-info/RECORD
