Metadata-Version: 2.4
Name: simple-rdp
Version: 0.1.0
Classifier: Development Status :: 4 - Beta
Classifier: Intended Audience :: Developers
Classifier: License :: OSI Approved :: MIT License
Classifier: Programming Language :: Python :: 3
Classifier: Programming Language :: Python :: 3.11
Classifier: Programming Language :: Python :: 3.12
Classifier: Programming Language :: Python :: 3.13
Classifier: Programming Language :: Python :: 3.14
Classifier: Programming Language :: Rust
Classifier: Topic :: System :: Networking
Classifier: Topic :: Multimedia :: Graphics :: Capture :: Screen Capture
Requires-Dist: pyspnego>=0.12.0
Requires-Dist: pyasn1>=0.6.2
Requires-Dist: pillow>=12.1.0
Requires-Dist: asn1crypto>=1.5.1
Requires-Dist: python-dotenv>=1.0.0
Requires-Dist: pytest>=8.0 ; extra == 'dev'
Requires-Dist: pytest-asyncio>=1.3.0 ; extra == 'dev'
Requires-Dist: pytest-cov>=7.0.0 ; extra == 'dev'
Requires-Dist: ruff>=0.14.14 ; extra == 'dev'
Requires-Dist: mypy>=1.19.1 ; extra == 'dev'
Requires-Dist: pre-commit>=4.5.1 ; extra == 'dev'
Requires-Dist: rich>=14.3.1 ; extra == 'dev'
Requires-Dist: python-docx>=1.2.0 ; extra == 'dev'
Provides-Extra: dev
License-File: LICENSE
Summary: A Python RDP client for automation - exposes screen capture and input transmission
Keywords: rdp,remote-desktop,automation,screen-capture
Home-Page: https://github.com/abi-jey/simple-rdp
License: MIT
Requires-Python: >=3.11
Project-URL: Documentation, https://github.com/abi-jey/simple-rdp#readme
Project-URL: Homepage, https://github.com/abi-jey/simple-rdp
Project-URL: Repository, https://github.com/abi-jey/simple-rdp
